mini_afsd/__init__.py
mini_afsd/__main__.py
mini_afsd/controller.py
mini_afsd/gui.py
mini_afsd/labjack_handler.py
mini_afsd/serial_processor.py
mini_afsd-1.2.1.dist-info/LICENSE.txt
mini_afsd-1.2.1.dist-info/METADATA
mini_afsd-1.2.1.dist-info/WHEEL
mini_afsd-1.2.1.dist-info/top_level.txt
mini_afsd-1.2.1.dist-info/RECORD
