Metadata-Version: 2.1
Name: mini-afsd
Version: 1.2.1
Summary: A program for controlling a miniturized additive friction stir deposition (AFSD) machine.
Home-page: https://github.com/RyTheGuy355/MiniAFSDCode
Author: Ryan Gottwald
Maintainer: Donald Erb
Maintainer-email: derb15@vt.edu
Project-URL: Source Code, https://github.com/RyTheGuy355/MiniAFSDCode
Project-URL: Documentation, https://mini_afsd.readthedocs.io
Keywords: AFSD,additive friction stir deposition,engineering
Classifier: Development Status :: 4 - Beta
Classifier: Intended Audience :: Science/Research
Classifier: Intended Audience :: Developers
Classifier: Programming Language :: Python :: 3
Classifier: Programming Language :: Python :: 3.7
Classifier: Programming Language :: Python :: 3.8
Classifier: Programming Language :: Python :: 3.9
Classifier: Programming Language :: Python :: 3.10
Classifier: Topic :: Scientific/Engineering
Classifier: Topic :: Scientific/Engineering :: Physics
Requires-Python: >=3.7
License-File: LICENSE.txt
Requires-Dist: labjack-ljm
Requires-Dist: matplotlib (>=3.4)
Requires-Dist: pyserial
